token_login_api/__init__.py
token_login_api/domain.py
token_login_api/views.py
token_login_api-1.0.0.dist-info/METADATA
token_login_api-1.0.0.dist-info/WHEEL
token_login_api-1.0.0.dist-info/top_level.txt
token_login_api-1.0.0.dist-info/RECORD
