Metadata-Version: 2.1
Name: token-login-api
Version: 1.0.0
Requires-Dist: attrs (==22.2.0)
Requires-Dist: click (==8.1.3)
Requires-Dist: exceptiongroup (==1.1.0)
Requires-Dist: Flask (==2.2.2)
Requires-Dist: iniconfig (==2.0.0)
Requires-Dist: itsdangerous (==2.1.2)
Requires-Dist: Jinja2 (==3.1.2)
Requires-Dist: MarkupSafe (==2.1.2)
Requires-Dist: packaging (==23.0)
Requires-Dist: pluggy (==1.0.0)
Requires-Dist: pytest (==7.2.1)
Requires-Dist: pytest-flask (==1.2.0)
Requires-Dist: tomli (==2.0.1)
Requires-Dist: Werkzeug (==2.2.2)
